devcon/__init__.py
devcon/cli.py
devcon/generator.py
devcon/models.py
devcon/validators.py
devcon/templates/common/p10k-lean.zsh
devcon/templates/data-science/Dockerfile.j2
devcon/templates/data-science/devcontainer.json.j2
devcon/templates/llm-finetuning/Dockerfile.j2
devcon/templates/llm-finetuning/devcontainer.json.j2
devcon/templates/web-dev/Dockerfile.j2
devcon/templates/web-dev/devcontainer.json.j2
devcon-0.1.2.dist-info/licenses/LICENSE
devcon-0.1.2.dist-info/METADATA
devcon-0.1.2.dist-info/WHEEL
devcon-0.1.2.dist-info/entry_points.txt
devcon-0.1.2.dist-info/top_level.txt
devcon-0.1.2.dist-info/RECORD
