Metadata-Version: 2.4
Name: devcon
Version: 0.1.2
Summary: Generate VS Code devcontainer configurations for MacOS
Author: DevCon Contributors
License: MIT
Project-URL: Homepage, https://gitlab.com/hoogvliets/devcon
Project-URL: Documentation, https://gitlab.com/hoogvliets/devcon#readme
Project-URL: Repository, https://gitlab.com/hoogvliets/devcon
Project-URL: Issues, https://gitlab.com/hoogvliets/devcon/-/issues
Keywords: devcontainer,docker,vscode,development,macos,data-science,llm,web-development
Classifier: Development Status :: 4 - Beta
Classifier: Intended Audience :: Developers
Classifier: License :: OSI Approved :: MIT License
Classifier: Operating System :: MacOS
Classifier: Programming Language :: Python :: 3
Classifier: Programming Language :: Python :: 3.9
Classifier: Programming Language :: Python :: 3.10
Classifier: Programming Language :: Python :: 3.11
Classifier: Programming Language :: Python :: 3.12
Classifier: Programming Language :: Python :: 3.13
Classifier: Topic :: Software Development :: Build Tools
Classifier: Topic :: Software Development :: Code Generators
Classifier: Environment :: Console
Requires-Python: >=3.9
License-File: LICENSE
Requires-Dist: click>=8.1.0
Requires-Dist: jinja2>=3.1.0
Provides-Extra: dev
Requires-Dist: pytest>=7.0; extra == "dev"
Requires-Dist: pytest-cov>=4.0; extra == "dev"
Requires-Dist: mypy>=1.0; extra == "dev"
Requires-Dist: ruff>=0.1.0; extra == "dev"
Requires-Dist: types-click; extra == "dev"
Dynamic: license-file
